richspot.py
richspot-1.0.4.dist-info/entry_points.txt
richspot-1.0.4.dist-info/LICENSE
richspot-1.0.4.dist-info/WHEEL
richspot-1.0.4.dist-info/METADATA
richspot-1.0.4.dist-info/RECORD
