Metadata-Version: 2.1
Name: richspot
Version: 1.0.4
Summary: ncspot discord rich presence
Keywords: Spotify,Spotify Rich Presence,Rich Presence,Ncspot,Ncspot Rich Presence,Discord,Discord Rich Presence,Spotify Connect
Author-email: Younes Ben El <ybenel@duck.com>
Requires-Python: >=3.8
Classifier: License :: OSI Approved :: GNU General Public License v3 (GPLv3)
Classifier: Operating System :: OS Independent
Classifier: Intended Audience :: End Users/Desktop
Classifier: Programming Language :: Python
Classifier: Programming Language :: Python :: 3.8
Classifier: Programming Language :: Python :: 3.9
Classifier: Programming Language :: Python :: 3.10
Classifier: Programming Language :: Python :: 3.11
Classifier: Programming Language :: Python :: 3.12
Requires-Dist: pypresence
Requires-Dist: requests
Requires-Dist: PyYaml
Project-URL: Documentation, https://github.com/m1ndo/RichSpot
Project-URL: Source, https://github.com/m1ndo/RichSpot
